bluemap/__init__.py
bluemap/_map.cpp
bluemap/_map.cpython-313-i386-linux-musl.so
bluemap/_map.pyx
bluemap/main.py
bluemap/stream.c
bluemap/stream.cpython-313-i386-linux-musl.so
bluemap/stream.pxd
bluemap/stream.pyx
bluemap/table.py
bluemap.libs/libgcc_s-887de51c.so.1
bluemap.libs/libstdc++-d6415257.so.6.0.33
bluemap-0.2.0a1.dist-info/LICENSE
bluemap-0.2.0a1.dist-info/METADATA
bluemap-0.2.0a1.dist-info/WHEEL
bluemap-0.2.0a1.dist-info/top_level.txt
bluemap-0.2.0a1.dist-info/RECORD
