Metadata-Version: 2.2
Name: bluemap
Version: 0.2.0a1
Summary: An influence map generator
Author-email: Blaumeis03 <dev@blaumeise03.de>
Maintainer-email: Blaumeis03 <dev@blaumeise03.de>
License: MIT License
Project-URL: Homepage, https://github.com/Blaumeise03/bluemap
Project-URL: Repository, https://github.com/Blaumeise03/bluemap.git
Project-URL: Documentation, https://blaumeise03.github.io/bluemap/
Project-URL: Issues, https://github.com/Blaumeise03/bluemap/issues
Classifier: Development Status :: 3 - Alpha
Classifier: Programming Language :: C++
Classifier: Programming Language :: Cython
Classifier: Programming Language :: Python :: 3
Classifier: Programming Language :: Python :: 3.12
Classifier: Programming Language :: Python :: 3.13
Classifier: Programming Language :: Python :: Implementation :: CPython
Classifier: Intended Audience :: Developers
Classifier: Typing :: Typed
Classifier: License :: OSI Approved :: MIT License
Requires-Python: >=3.12
License-File: LICENSE
Provides-Extra: cli
Requires-Dist: Pillow>=11.0.0; extra == "cli"
Requires-Dist: pymysql>=1.0.0; extra == "cli"
Provides-Extra: table
Requires-Dist: Pillow>=11.0.0; extra == "table"
Provides-Extra: minimal
Provides-Extra: dev
Requires-Dist: Pillow>=11.0.0; extra == "dev"
Requires-Dist: pymysql>=1.0.0; extra == "dev"
Requires-Dist: psutil~=7.0.0; extra == "dev"
Requires-Dist: numpy~=2.2.3; extra == "dev"
Requires-Dist: opencv-python~=4.11.0; extra == "dev"
